embed_anything/__init__.py
embed_anything/_embed_anything.cpython-314-darwin.so
embed_anything/_embed_anything.pyi
embed_anything/libiomp5md.dll
embed_anything/py.typed
embed_anything/vectordb.py
embed_anything_gpu-0.7.0.dist-info/METADATA
embed_anything_gpu-0.7.0.dist-info/WHEEL
embed_anything_gpu-0.7.0.dist-info/licenses/LICENSE
embed_anything_gpu-0.7.0.dist-info/RECORD
