Metadata-Version: 2.4
Name: embed_anything_gpu
Version: 0.7.0
Classifier: Programming Language :: Python :: 3.10
Classifier: Programming Language :: Python :: 3.11
Classifier: Programming Language :: Python :: 3.12
Classifier: Programming Language :: Python :: 3.13
Classifier: Programming Language :: Python :: 3.14
Classifier: License :: OSI Approved :: MIT License
Requires-Dist: onnxruntime-gpu==1.22.0
License-File: LICENSE
Summary: Embed anything at lightning speed
Requires-Python: >=3.10
Project-URL: Homepage, https://github.com/StarlightSearch/EmbedAnything/tree/main
